{
  "updated_at": "2026-07-10T17:20:57.619614+00:00",
  "latest_time": "2026-07-11 02:10",
  "latest_close": 69205.0,
  "signal": "様子見",
  "score": -1.5,
  "score_normalized": -21,
  "reasons": [
    "RSI=71.4 (overbought)"
  ],
  "stop_price": null,
  "take_profit": null,
  "risk_reward": null,
  "score_breakdown": {
    "MA": 0,
    "RSI": -1.5,
    "MACD": 0,
    "BB": 0
  },
  "stars": 2,
  "star_label": "弱い売り",
  "current_state": [
    "MA5(69198)がMA25(69099)を上回っており、短期は上昇基調",
    "RSI=71.4で過熱(買われすぎ)水準",
    "MACDヒストグラムはマイナス(下降モメンタム)",
    "価格はボリンジャーバンドの通常レンジ内"
  ],
  "summary": "短期は上昇基調、MACDは下向き、RSI(71)が過熱気味のため「様子見」と判定。 1時間足では「買い」。 複合判定は「買い優勢」。",
  "atr": 51.07,
  "suggested_levels": {
    "buy": {
      "entry": 69205.0,
      "sl": 69051.79,
      "tp1": 69434.82,
      "tp2": 69664.64,
      "rr1": 1.5,
      "rr2": 3.0
    },
    "sell": {
      "entry": 69205.0,
      "sl": 69358.21,
      "tp1": 68975.18,
      "tp2": 68745.36,
      "rr1": 1.5,
      "rr2": 3.0
    }
  },
  "daily_change": 350.0,
  "daily_change_pct": 0.51,
  "candles": [
    {
      "time": "2026-07-10 17:55",
      "open": 68800.0,
      "high": 68815.0,
      "low": 68745.0,
      "close": 68745.0,
      "ma5": 68724.0,
      "ma25": 68756.4,
      "rsi": 48.5,
      "macd": -28.96,
      "macd_signal": -42.94,
      "macd_hist": 13.98,
      "bb_upper": 68957.27,
      "bb_lower": 68519.23
    },
    {
      "time": "2026-07-10 18:00",
      "open": 68750.0,
      "high": 68765.0,
      "low": 68635.0,
      "close": 68750.0,
      "ma5": 68750.0,
      "ma25": 68752.8,
      "rsi": 50.6,
      "macd": -24.42,
      "macd_signal": -39.23,
      "macd_hist": 14.81,
      "bb_upper": 68949.81,
      "bb_lower": 68519.19
    },
    {
      "time": "2026-07-10 18:05",
      "open": 68750.0,
      "high": 68775.0,
      "low": 68720.0,
      "close": 68770.0,
      "ma5": 68762.0,
      "ma25": 68751.2,
      "rsi": 50.6,
      "macd": -18.99,
      "macd_signal": -35.19,
      "macd_hist": 16.19,
      "bb_upper": 68932.99,
      "bb_lower": 68524.51
    },
    {
      "time": "2026-07-10 18:10",
      "open": 68765.0,
      "high": 68810.0,
      "low": 68765.0,
      "close": 68800.0,
      "ma5": 68773.0,
      "ma25": 68750.0,
      "rsi": 76.3,
      "macd": -12.13,
      "macd_signal": -30.57,
      "macd_hist": 18.44,
      "bb_upper": 68910.99,
      "bb_lower": 68535.01
    },
    {
      "time": "2026-07-10 18:15",
      "open": 68800.0,
      "high": 68875.0,
      "low": 68800.0,
      "close": 68875.0,
      "ma5": 68788.0,
      "ma25": 68751.4,
      "rsi": 75.2,
      "macd": -0.63,
      "macd_signal": -24.59,
      "macd_hist": 23.95,
      "bb_upper": 68905.06,
      "bb_lower": 68538.44
    },
    {
      "time": "2026-07-10 18:20",
      "open": 68865.0,
      "high": 68865.0,
      "low": 68795.0,
      "close": 68805.0,
      "ma5": 68800.0,
      "ma25": 68750.6,
      "rsi": 62.0,
      "macd": 2.8,
      "macd_signal": -19.11,
      "macd_hist": 21.91,
      "bb_upper": 68890.43,
      "bb_lower": 68545.57
    },
    {
      "time": "2026-07-10 18:25",
      "open": 68805.0,
      "high": 68815.0,
      "low": 68765.0,
      "close": 68795.0,
      "ma5": 68809.0,
      "ma25": 68749.4,
      "rsi": 59.4,
      "macd": 4.66,
      "macd_signal": -14.36,
      "macd_hist": 19.01,
      "bb_upper": 68893.61,
      "bb_lower": 68544.89
    },
    {
      "time": "2026-07-10 18:30",
      "open": 68775.0,
      "high": 68820.0,
      "low": 68765.0,
      "close": 68820.0,
      "ma5": 68819.0,
      "ma25": 68746.8,
      "rsi": 61.3,
      "macd": 8.05,
      "macd_signal": -9.87,
      "macd_hist": 17.93,
      "bb_upper": 68903.2,
      "bb_lower": 68543.3
    },
    {
      "time": "2026-07-10 18:35",
      "open": 68830.0,
      "high": 68855.0,
      "low": 68810.0,
      "close": 68850.0,
      "ma5": 68829.0,
      "ma25": 68744.2,
      "rsi": 63.8,
      "macd": 13.02,
      "macd_signal": -5.3,
      "macd_hist": 18.31,
      "bb_upper": 68915.88,
      "bb_lower": 68539.62
    },
    {
      "time": "2026-07-10 18:40",
      "open": 68830.0,
      "high": 68830.0,
      "low": 68790.0,
      "close": 68795.0,
      "ma5": 68813.0,
      "ma25": 68740.0,
      "rsi": 66.1,
      "macd": 12.37,
      "macd_signal": -1.76,
      "macd_hist": 14.13,
      "bb_upper": 68899.06,
      "bb_lower": 68585.94
    },
    {
      "time": "2026-07-10 18:45",
      "open": 68815.0,
      "high": 68860.0,
      "low": 68815.0,
      "close": 68840.0,
      "ma5": 68820.0,
      "ma25": 68738.4,
      "rsi": 68.3,
      "macd": 15.31,
      "macd_signal": 1.65,
      "macd_hist": 13.66,
      "bb_upper": 68901.57,
      "bb_lower": 68607.43
    },
    {
      "time": "2026-07-10 18:50",
      "open": 68840.0,
      "high": 68895.0,
      "low": 68840.0,
      "close": 68885.0,
      "ma5": 68838.0,
      "ma25": 68743.0,
      "rsi": 65.8,
      "macd": 21.03,
      "macd_signal": 5.53,
      "macd_hist": 15.5,
      "bb_upper": 68918.04,
      "bb_lower": 68611.96
    },
    {
      "time": "2026-07-10 18:55",
      "open": 68875.0,
      "high": 68875.0,
      "low": 68845.0,
      "close": 68845.0,
      "ma5": 68843.0,
      "ma25": 68747.2,
      "rsi": 58.9,
      "macd": 22.08,
      "macd_signal": 8.84,
      "macd_hist": 13.24,
      "bb_upper": 68925.8,
      "bb_lower": 68619.2
    },
    {
      "time": "2026-07-10 19:00",
      "open": 68855.0,
      "high": 68890.0,
      "low": 68855.0,
      "close": 68885.0,
      "ma5": 68850.0,
      "ma25": 68752.2,
      "rsi": 57.8,
      "macd": 25.84,
      "macd_signal": 12.24,
      "macd_hist": 13.6,
      "bb_upper": 68938.59,
      "bb_lower": 68625.41
    },
    {
      "time": "2026-07-10 19:05",
      "open": 68910.0,
      "high": 68925.0,
      "low": 68905.0,
      "close": 68920.0,
      "ma5": 68875.0,
      "ma25": 68769.0,
      "rsi": 66.7,
      "macd": 31.29,
      "macd_signal": 16.05,
      "macd_hist": 15.24,
      "bb_upper": 68955.33,
      "bb_lower": 68631.67
    },
    {
      "time": "2026-07-10 19:10",
      "open": 68905.0,
      "high": 68925.0,
      "low": 68905.0,
      "close": 68920.0,
      "ma5": 68891.0,
      "ma25": 68781.8,
      "rsi": 66.3,
      "macd": 35.2,
      "macd_signal": 19.88,
      "macd_hist": 15.32,
      "bb_upper": 68956.64,
      "bb_lower": 68660.86
    },
    {
      "time": "2026-07-10 19:15",
      "open": 68935.0,
      "high": 68940.0,
      "low": 68920.0,
      "close": 68920.0,
      "ma5": 68898.0,
      "ma25": 68791.6,
      "rsi": 65.0,
      "macd": 37.86,
      "macd_signal": 23.48,
      "macd_hist": 14.39,
      "bb_upper": 68950.36,
      "bb_lower": 68697.14
    },
    {
      "time": "2026-07-10 19:20",
      "open": 68935.0,
      "high": 68975.0,
      "low": 68890.0,
      "close": 68920.0,
      "ma5": 68913.0,
      "ma25": 68800.6,
      "rsi": 62.8,
      "macd": 39.52,
      "macd_signal": 26.68,
      "macd_hist": 12.83,
      "bb_upper": 68955.87,
      "bb_lower": 68712.63
    },
    {
      "time": "2026-07-10 19:25",
      "open": 68920.0,
      "high": 68925.0,
      "low": 68890.0,
      "close": 68925.0,
      "ma5": 68921.0,
      "ma25": 68809.8,
      "rsi": 56.2,
      "macd": 40.76,
      "macd_signal": 29.5,
      "macd_hist": 11.26,
      "bb_upper": 68963.7,
      "bb_lower": 68722.8
    },
    {
      "time": "2026-07-10 19:30",
      "open": 68990.0,
      "high": 69020.0,
      "low": 68985.0,
      "close": 69000.0,
      "ma5": 68937.0,
      "ma25": 68822.2,
      "rsi": 74.1,
      "macd": 47.25,
      "macd_signal": 33.05,
      "macd_hist": 14.2,
      "bb_upper": 68990.6,
      "bb_lower": 68715.9
    },
    {
      "time": "2026-07-10 19:35",
      "open": 68995.0,
      "high": 69000.0,
      "low": 68965.0,
      "close": 69000.0,
      "ma5": 68953.0,
      "ma25": 68837.6,
      "rsi": 75.9,
      "macd": 51.8,
      "macd_signal": 36.8,
      "macd_hist": 15.0,
      "bb_upper": 69008.3,
      "bb_lower": 68723.7
    },
    {
      "time": "2026-07-10 19:40",
      "open": 68990.0,
      "high": 69035.0,
      "low": 68985.0,
      "close": 69030.0,
      "ma5": 68975.0,
      "ma25": 68854.0,
      "rsi": 76.2,
      "macd": 57.17,
      "macd_signal": 40.87,
      "macd_hist": 16.3,
      "bb_upper": 69029.17,
      "bb_lower": 68730.83
    },
    {
      "time": "2026-07-10 19:45",
      "open": 69015.0,
      "high": 69025.0,
      "low": 68995.0,
      "close": 69020.0,
      "ma5": 68995.0,
      "ma25": 68866.4,
      "rsi": 72.4,
      "macd": 59.93,
      "macd_signal": 44.69,
      "macd_hist": 15.24,
      "bb_upper": 69044.73,
      "bb_lower": 68740.27
    },
    {
      "time": "2026-07-10 19:50",
      "open": 69005.0,
      "high": 69015.0,
      "low": 68985.0,
      "close": 68985.0,
      "ma5": 69007.0,
      "ma25": 68876.0,
      "rsi": 76.4,
      "macd": 58.61,
      "macd_signal": 47.47,
      "macd_hist": 11.14,
      "bb_upper": 69052.79,
      "bb_lower": 68750.71
    },
    {
      "time": "2026-07-10 19:55",
      "open": 68975.0,
      "high": 69000.0,
      "low": 68965.0,
      "close": 68985.0,
      "ma5": 69004.0,
      "ma25": 68883.4,
      "rsi": 73.0,
      "macd": 56.91,
      "macd_signal": 49.36,
      "macd_hist": 7.55,
      "bb_upper": 69062.15,
      "bb_lower": 68752.35
    },
    {
      "time": "2026-07-10 20:00",
      "open": 68995.0,
      "high": 69055.0,
      "low": 68995.0,
      "close": 69030.0,
      "ma5": 69010.0,
      "ma25": 68894.8,
      "rsi": 73.0,
      "macd": 58.52,
      "macd_signal": 51.19,
      "macd_hist": 7.33,
      "bb_upper": 69074.81,
      "bb_lower": 68762.19
    },
    {
      "time": "2026-07-10 20:05",
      "open": 69035.0,
      "high": 69035.0,
      "low": 69010.0,
      "close": 69030.0,
      "ma5": 69010.0,
      "ma25": 68906.0,
      "rsi": 83.6,
      "macd": 59.12,
      "macd_signal": 52.78,
      "macd_hist": 6.34,
      "bb_upper": 69082.75,
      "bb_lower": 68777.75
    },
    {
      "time": "2026-07-10 20:10",
      "open": 69015.0,
      "high": 69065.0,
      "low": 69015.0,
      "close": 69040.0,
      "ma5": 69014.0,
      "ma25": 68916.8,
      "rsi": 81.6,
      "macd": 59.7,
      "macd_signal": 54.16,
      "macd_hist": 5.54,
      "bb_upper": 69092.0,
      "bb_lower": 68790.5
    },
    {
      "time": "2026-07-10 20:15",
      "open": 69050.0,
      "high": 69085.0,
      "low": 69050.0,
      "close": 69050.0,
      "ma5": 69027.0,
      "ma25": 68926.8,
      "rsi": 79.5,
      "macd": 60.28,
      "macd_signal": 55.39,
      "macd_hist": 4.9,
      "bb_upper": 69103.04,
      "bb_lower": 68799.46
    },
    {
      "time": "2026-07-10 20:20",
      "open": 69055.0,
      "high": 69060.0,
      "low": 69035.0,
      "close": 69060.0,
      "ma5": 69042.0,
      "ma25": 68934.2,
      "rsi": 80.4,
      "macd": 60.85,
      "macd_signal": 56.48,
      "macd_hist": 4.37,
      "bb_upper": 69104.68,
      "bb_lower": 68824.32
    },
    {
      "time": "2026-07-10 20:25",
      "open": 69050.0,
      "high": 69050.0,
      "low": 68970.0,
      "close": 68980.0,
      "ma5": 69032.0,
      "ma25": 68941.2,
      "rsi": 59.7,
      "macd": 54.22,
      "macd_signal": 56.03,
      "macd_hist": -1.81,
      "bb_upper": 69098.91,
      "bb_lower": 68844.09
    },
    {
      "time": "2026-07-10 20:30",
      "open": 68970.0,
      "high": 68970.0,
      "low": 68910.0,
      "close": 68930.0,
      "ma5": 69012.0,
      "ma25": 68946.6,
      "rsi": 51.4,
      "macd": 44.41,
      "macd_signal": 53.7,
      "macd_hist": -9.29,
      "bb_upper": 69096.22,
      "bb_lower": 68851.28
    },
    {
      "time": "2026-07-10 20:35",
      "open": 68935.0,
      "high": 68935.0,
      "low": 68885.0,
      "close": 68905.0,
      "ma5": 68985.0,
      "ma25": 68950.0,
      "rsi": 47.4,
      "macd": 34.23,
      "macd_signal": 49.81,
      "macd_hist": -15.58,
      "bb_upper": 69088.4,
      "bb_lower": 68865.1
    },
    {
      "time": "2026-07-10 20:40",
      "open": 68900.0,
      "high": 68965.0,
      "low": 68900.0,
      "close": 68965.0,
      "ma5": 68968.0,
      "ma25": 68954.6,
      "rsi": 45.2,
      "macd": 30.65,
      "macd_signal": 45.98,
      "macd_hist": -15.33,
      "bb_upper": 69083.98,
      "bb_lower": 68877.52
    },
    {
      "time": "2026-07-10 20:45",
      "open": 68930.0,
      "high": 68950.0,
      "low": 68930.0,
      "close": 68945.0,
      "ma5": 68945.0,
      "ma25": 68960.6,
      "rsi": 42.9,
      "macd": 25.9,
      "macd_signal": 41.96,
      "macd_hist": -16.06,
      "bb_upper": 69082.7,
      "bb_lower": 68881.3
    },
    {
      "time": "2026-07-10 20:50",
      "open": 68935.0,
      "high": 68955.0,
      "low": 68900.0,
      "close": 68900.0,
      "ma5": 68929.0,
      "ma25": 68963.0,
      "rsi": 33.8,
      "macd": 18.3,
      "macd_signal": 37.23,
      "macd_hist": -18.93,
      "bb_upper": 69084.65,
      "bb_lower": 68877.35
    },
    {
      "time": "2026-07-10 20:55",
      "open": 68895.0,
      "high": 68915.0,
      "low": 68860.0,
      "close": 68915.0,
      "ma5": 68926.0,
      "ma25": 68964.2,
      "rsi": 37.0,
      "macd": 13.32,
      "macd_signal": 32.45,
      "macd_hist": -19.12,
      "bb_upper": 69085.04,
      "bb_lower": 68876.46
    },
    {
      "time": "2026-07-10 21:00",
      "open": 68930.0,
      "high": 68930.0,
      "low": 68785.0,
      "close": 68795.0,
      "ma5": 68904.0,
      "ma25": 68962.2,
      "rsi": 30.6,
      "macd": -0.29,
      "macd_signal": 25.9,
      "macd_hist": -26.19,
      "bb_upper": 69105.64,
      "bb_lower": 68843.36
    },
    {
      "time": "2026-07-10 21:05",
      "open": 68760.0,
      "high": 68815.0,
      "low": 68735.0,
      "close": 68815.0,
      "ma5": 68874.0,
      "ma25": 68959.4,
      "rsi": 33.3,
      "macd": -9.37,
      "macd_signal": 18.85,
      "macd_hist": -28.21,
      "bb_upper": 69117.03,
      "bb_lower": 68820.97
    },
    {
      "time": "2026-07-10 21:10",
      "open": 68820.0,
      "high": 69125.0,
      "low": 68780.0,
      "close": 68965.0,
      "ma5": 68878.0,
      "ma25": 68961.2,
      "rsi": 44.7,
      "macd": -4.4,
      "macd_signal": 14.2,
      "macd_hist": -18.6,
      "bb_upper": 69114.56,
      "bb_lower": 68819.94
    },
    {
      "time": "2026-07-10 21:15",
      "open": 68960.0,
      "high": 68985.0,
      "low": 68865.0,
      "close": 68870.0,
      "ma5": 68872.0,
      "ma25": 68959.2,
      "rsi": 38.7,
      "macd": -8.04,
      "macd_signal": 9.75,
      "macd_hist": -17.79,
      "bb_upper": 69113.35,
      "bb_lower": 68808.15
    },
    {
      "time": "2026-07-10 21:20",
      "open": 68890.0,
      "high": 68930.0,
      "low": 68870.0,
      "close": 68900.0,
      "ma5": 68869.0,
      "ma25": 68958.4,
      "rsi": 40.4,
      "macd": -8.4,
      "macd_signal": 6.12,
      "macd_hist": -14.52,
      "bb_upper": 69105.5,
      "bb_lower": 68803.0
    },
    {
      "time": "2026-07-10 21:25",
      "open": 68895.0,
      "high": 68925.0,
      "low": 68870.0,
      "close": 68870.0,
      "ma5": 68884.0,
      "ma25": 68956.4,
      "rsi": 38.0,
      "macd": -10.99,
      "macd_signal": 2.7,
      "macd_hist": -13.69,
      "bb_upper": 69099.14,
      "bb_lower": 68794.36
    },
    {
      "time": "2026-07-10 21:30",
      "open": 68865.0,
      "high": 68875.0,
      "low": 68835.0,
      "close": 68860.0,
      "ma5": 68893.0,
      "ma25": 68953.8,
      "rsi": 36.7,
      "macd": -13.69,
      "macd_signal": -0.58,
      "macd_hist": -13.11,
      "bb_upper": 69096.5,
      "bb_lower": 68784.5
    },
    {
      "time": "2026-07-10 21:35",
      "open": 68850.0,
      "high": 68900.0,
      "low": 68815.0,
      "close": 68900.0,
      "ma5": 68880.0,
      "ma25": 68949.8,
      "rsi": 44.4,
      "macd": -12.45,
      "macd_signal": -2.95,
      "macd_hist": -9.5,
      "bb_upper": 69091.78,
      "bb_lower": 68780.72
    },
    {
      "time": "2026-07-10 21:40",
      "open": 68920.0,
      "high": 68925.0,
      "low": 68815.0,
      "close": 68825.0,
      "ma5": 68871.0,
      "ma25": 68942.8,
      "rsi": 42.9,
      "macd": -17.33,
      "macd_signal": -5.83,
      "macd_hist": -11.5,
      "bb_upper": 69082.53,
      "bb_lower": 68769.47
    },
    {
      "time": "2026-07-10 21:45",
      "open": 68810.0,
      "high": 68830.0,
      "low": 68780.0,
      "close": 68800.0,
      "ma5": 68851.0,
      "ma25": 68933.6,
      "rsi": 42.9,
      "macd": -22.94,
      "macd_signal": -9.25,
      "macd_hist": -13.69,
      "bb_upper": 69072.64,
      "bb_lower": 68756.36
    },
    {
      "time": "2026-07-10 21:50",
      "open": 68810.0,
      "high": 68830.0,
      "low": 68790.0,
      "close": 68800.0,
      "ma5": 68837.0,
      "ma25": 68924.8,
      "rsi": 37.8,
      "macd": -27.08,
      "macd_signal": -12.82,
      "macd_hist": -14.26,
      "bb_upper": 69056.93,
      "bb_lower": 68748.07
    },
    {
      "time": "2026-07-10 21:55",
      "open": 68800.0,
      "high": 68815.0,
      "low": 68760.0,
      "close": 68780.0,
      "ma5": 68821.0,
      "ma25": 68916.6,
      "rsi": 37.8,
      "macd": -31.61,
      "macd_signal": -16.58,
      "macd_hist": -15.03,
      "bb_upper": 69036.17,
      "bb_lower": 68741.83
    },
    {
      "time": "2026-07-10 22:00",
      "open": 68760.0,
      "high": 68815.0,
      "low": 68690.0,
      "close": 68750.0,
      "ma5": 68791.0,
      "ma25": 68907.2,
      "rsi": 38.6,
      "macd": -37.19,
      "macd_signal": -20.7,
      "macd_hist": -16.49,
      "bb_upper": 69009.73,
      "bb_lower": 68737.27
    },
    {
      "time": "2026-07-10 22:05",
      "open": 68750.0,
      "high": 68800.0,
      "low": 68750.0,
      "close": 68760.0,
      "ma5": 68778.0,
      "ma25": 68896.4,
      "rsi": 38.2,
      "macd": -40.34,
      "macd_signal": -24.63,
      "macd_hist": -15.71,
      "bb_upper": 68998.05,
      "bb_lower": 68726.95
    },
    {
      "time": "2026-07-10 22:10",
      "open": 68765.0,
      "high": 68770.0,
      "low": 68735.0,
      "close": 68770.0,
      "ma5": 68772.0,
      "ma25": 68886.0,
      "rsi": 47.7,
      "macd": -41.55,
      "macd_signal": -28.01,
      "macd_hist": -13.54,
      "bb_upper": 68992.15,
      "bb_lower": 68716.85
    },
    {
      "time": "2026-07-10 22:15",
      "open": 68755.0,
      "high": 68775.0,
      "low": 68730.0,
      "close": 68760.0,
      "ma5": 68764.0,
      "ma25": 68874.8,
      "rsi": 44.9,
      "macd": -42.83,
      "macd_signal": -30.98,
      "macd_hist": -11.85,
      "bb_upper": 68988.91,
      "bb_lower": 68705.59
    },
    {
      "time": "2026-07-10 22:20",
      "open": 68780.0,
      "high": 68780.0,
      "low": 68740.0,
      "close": 68740.0,
      "ma5": 68756.0,
      "ma25": 68862.4,
      "rsi": 22.2,
      "macd": -44.93,
      "macd_signal": -33.77,
      "macd_hist": -11.17,
      "bb_upper": 68973.98,
      "bb_lower": 68698.02
    },
    {
      "time": "2026-07-10 22:25",
      "open": 68760.0,
      "high": 68785.0,
      "low": 68650.0,
      "close": 68680.0,
      "ma5": 68742.0,
      "ma25": 68847.2,
      "rsi": 24.3,
      "macd": -50.86,
      "macd_signal": -37.18,
      "macd_hist": -13.67,
      "bb_upper": 68967.39,
      "bb_lower": 68678.11
    },
    {
      "time": "2026-07-10 22:30",
      "open": 68690.0,
      "high": 68790.0,
      "low": 68625.0,
      "close": 68695.0,
      "ma5": 68729.0,
      "ma25": 68835.8,
      "rsi": 21.1,
      "macd": -53.72,
      "macd_signal": -40.49,
      "macd_hist": -13.23,
      "bb_upper": 68963.03,
      "bb_lower": 68661.97
    },
    {
      "time": "2026-07-10 22:35",
      "open": 68680.0,
      "high": 68710.0,
      "low": 68580.0,
      "close": 68595.0,
      "ma5": 68694.0,
      "ma25": 68822.4,
      "rsi": 17.6,
      "macd": -63.33,
      "macd_signal": -45.06,
      "macd_hist": -18.27,
      "bb_upper": 68967.75,
      "bb_lower": 68625.25
    },
    {
      "time": "2026-07-10 22:40",
      "open": 68605.0,
      "high": 68685.0,
      "low": 68455.0,
      "close": 68635.0,
      "ma5": 68669.0,
      "ma25": 68811.6,
      "rsi": 25.3,
      "macd": -66.95,
      "macd_signal": -49.44,
      "macd_hist": -17.51,
      "bb_upper": 68974.37,
      "bb_lower": 68602.63
    },
    {
      "time": "2026-07-10 22:45",
      "open": 68635.0,
      "high": 68855.0,
      "low": 68635.0,
      "close": 68825.0,
      "ma5": 68686.0,
      "ma25": 68806.0,
      "rsi": 43.8,
      "macd": -53.86,
      "macd_signal": -50.32,
      "macd_hist": -3.54,
      "bb_upper": 68975.23,
      "bb_lower": 68602.77
    },
    {
      "time": "2026-07-10 22:50",
      "open": 68815.0,
      "high": 68915.0,
      "low": 68770.0,
      "close": 68845.0,
      "ma5": 68719.0,
      "ma25": 68802.0,
      "rsi": 51.8,
      "macd": -41.4,
      "macd_signal": -48.54,
      "macd_hist": 7.14,
      "bb_upper": 68952.31,
      "bb_lower": 68613.69
    },
    {
      "time": "2026-07-10 22:55",
      "open": 68840.0,
      "high": 68840.0,
      "low": 68715.0,
      "close": 68745.0,
      "ma5": 68729.0,
      "ma25": 68795.8,
      "rsi": 45.6,
      "macd": -39.14,
      "macd_signal": -46.66,
      "macd_hist": 7.52,
      "bb_upper": 68941.71,
      "bb_lower": 68611.79
    },
    {
      "time": "2026-07-10 23:00",
      "open": 68765.0,
      "high": 68835.0,
      "low": 68735.0,
      "close": 68795.0,
      "ma5": 68769.0,
      "ma25": 68791.0,
      "rsi": 49.6,
      "macd": -32.94,
      "macd_signal": -43.91,
      "macd_hist": 10.98,
      "bb_upper": 68926.32,
      "bb_lower": 68616.68
    },
    {
      "time": "2026-07-10 23:05",
      "open": 68795.0,
      "high": 68845.0,
      "low": 68745.0,
      "close": 68845.0,
      "ma5": 68811.0,
      "ma25": 68793.0,
      "rsi": 54.6,
      "macd": -23.71,
      "macd_signal": -39.87,
      "macd_hist": 16.16,
      "bb_upper": 68922.1,
      "bb_lower": 68618.4
    },
    {
      "time": "2026-07-10 23:10",
      "open": 68850.0,
      "high": 68855.0,
      "low": 68760.0,
      "close": 68805.0,
      "ma5": 68807.0,
      "ma25": 68792.6,
      "rsi": 53.8,
      "macd": -19.4,
      "macd_signal": -35.78,
      "macd_hist": 16.37,
      "bb_upper": 68914.42,
      "bb_lower": 68620.58
    },
    {
      "time": "2026-07-10 23:15",
      "open": 68805.0,
      "high": 68845.0,
      "low": 68745.0,
      "close": 68805.0,
      "ma5": 68799.0,
      "ma25": 68786.2,
      "rsi": 53.2,
      "macd": -15.81,
      "macd_signal": -31.78,
      "macd_hist": 15.98,
      "bb_upper": 68897.25,
      "bb_lower": 68628.25
    },
    {
      "time": "2026-07-10 23:20",
      "open": 68810.0,
      "high": 68820.0,
      "low": 68690.0,
      "close": 68785.0,
      "ma5": 68807.0,
      "ma25": 68782.8,
      "rsi": 51.0,
      "macd": -14.41,
      "macd_signal": -28.31,
      "macd_hist": 13.9,
      "bb_upper": 68892.51,
      "bb_lower": 68628.99
    },
    {
      "time": "2026-07-10 23:25",
      "open": 68805.0,
      "high": 68975.0,
      "low": 68770.0,
      "close": 68890.0,
      "ma5": 68826.0,
      "ma25": 68782.4,
      "rsi": 58.0,
      "macd": -4.77,
      "macd_signal": -23.6,
      "macd_hist": 18.83,
      "bb_upper": 68908.32,
      "bb_lower": 68622.18
    },
    {
      "time": "2026-07-10 23:30",
      "open": 68905.0,
      "high": 69035.0,
      "low": 68230.0,
      "close": 68745.0,
      "ma5": 68806.0,
      "ma25": 68777.4,
      "rsi": 50.3,
      "macd": -8.73,
      "macd_signal": -20.63,
      "macd_hist": 11.9,
      "bb_upper": 68904.87,
      "bb_lower": 68620.13
    },
    {
      "time": "2026-07-10 23:35",
      "open": 68775.0,
      "high": 68870.0,
      "low": 68720.0,
      "close": 68795.0,
      "ma5": 68804.0,
      "ma25": 68774.8,
      "rsi": 56.2,
      "macd": -7.75,
      "macd_signal": -18.05,
      "macd_hist": 10.3,
      "bb_upper": 68906.16,
      "bb_lower": 68620.34
    },
    {
      "time": "2026-07-10 23:40",
      "open": 68810.0,
      "high": 68915.0,
      "low": 68770.0,
      "close": 68890.0,
      "ma5": 68821.0,
      "ma25": 68774.4,
      "rsi": 59.7,
      "macd": 0.69,
      "macd_signal": -14.3,
      "macd_hist": 14.99,
      "bb_upper": 68923.75,
      "bb_lower": 68616.75
    },
    {
      "time": "2026-07-10 23:45",
      "open": 68880.0,
      "high": 68945.0,
      "low": 68835.0,
      "close": 68945.0,
      "ma5": 68853.0,
      "ma25": 68779.2,
      "rsi": 68.2,
      "macd": 11.68,
      "macd_signal": -9.11,
      "macd_hist": 20.79,
      "bb_upper": 68951.57,
      "bb_lower": 68607.43
    },
    {
      "time": "2026-07-10 23:50",
      "open": 68935.0,
      "high": 68965.0,
      "low": 68885.0,
      "close": 68910.0,
      "ma5": 68857.0,
      "ma25": 68783.6,
      "rsi": 64.4,
      "macd": 17.37,
      "macd_signal": -3.81,
      "macd_hist": 21.18,
      "bb_upper": 68968.07,
      "bb_lower": 68604.93
    },
    {
      "time": "2026-07-10 23:55",
      "open": 68910.0,
      "high": 68930.0,
      "low": 68840.0,
      "close": 68855.0,
      "ma5": 68879.0,
      "ma25": 68785.8,
      "rsi": 51.8,
      "macd": 17.24,
      "macd_signal": 0.4,
      "macd_hist": 16.84,
      "bb_upper": 68974.87,
      "bb_lower": 68607.63
    },
    {
      "time": "2026-07-11 00:00",
      "open": 68865.0,
      "high": 68880.0,
      "low": 68765.0,
      "close": 68775.0,
      "ma5": 68875.0,
      "ma25": 68785.6,
      "rsi": 46.0,
      "macd": 10.56,
      "macd_signal": 2.43,
      "macd_hist": 8.13,
      "bb_upper": 68975.22,
      "bb_lower": 68610.78
    },
    {
      "time": "2026-07-11 00:05",
      "open": 68780.0,
      "high": 68900.0,
      "low": 68750.0,
      "close": 68890.0,
      "ma5": 68875.0,
      "ma25": 68791.2,
      "rsi": 58.1,
      "macd": 14.38,
      "macd_signal": 4.82,
      "macd_hist": 9.56,
      "bb_upper": 68982.48,
      "bb_lower": 68624.52
    },
    {
      "time": "2026-07-11 00:10",
      "open": 68905.0,
      "high": 68945.0,
      "low": 68895.0,
      "close": 68930.0,
      "ma5": 68872.0,
      "ma25": 68798.0,
      "rsi": 57.6,
      "macd": 20.4,
      "macd_signal": 7.93,
      "macd_hist": 12.46,
      "bb_upper": 68995.09,
      "bb_lower": 68635.41
    },
    {
      "time": "2026-07-11 00:15",
      "open": 68950.0,
      "high": 69140.0,
      "low": 68935.0,
      "close": 69060.0,
      "ma5": 68902.0,
      "ma25": 68809.6,
      "rsi": 61.1,
      "macd": 35.25,
      "macd_signal": 13.4,
      "macd_hist": 21.85,
      "bb_upper": 69018.68,
      "bb_lower": 68658.32
    },
    {
      "time": "2026-07-11 00:20",
      "open": 69085.0,
      "high": 69140.0,
      "low": 69060.0,
      "close": 69075.0,
      "ma5": 68946.0,
      "ma25": 68822.2,
      "rsi": 64.4,
      "macd": 47.68,
      "macd_signal": 20.25,
      "macd_hist": 27.43,
      "bb_upper": 69043.48,
      "bb_lower": 68677.52
    },
    {
      "time": "2026-07-11 00:25",
      "open": 69090.0,
      "high": 69155.0,
      "low": 69075.0,
      "close": 69130.0,
      "ma5": 69017.0,
      "ma25": 68837.8,
      "rsi": 66.3,
      "macd": 61.27,
      "macd_signal": 28.46,
      "macd_hist": 32.81,
      "bb_upper": 69093.76,
      "bb_lower": 68657.74
    },
    {
      "time": "2026-07-11 00:30",
      "open": 69135.0,
      "high": 69140.0,
      "low": 69065.0,
      "close": 69095.0,
      "ma5": 69058.0,
      "ma25": 68854.4,
      "rsi": 65.3,
      "macd": 68.42,
      "macd_signal": 36.45,
      "macd_hist": 31.97,
      "bb_upper": 69126.56,
      "bb_lower": 68649.94
    },
    {
      "time": "2026-07-11 00:35",
      "open": 69095.0,
      "high": 69095.0,
      "low": 68965.0,
      "close": 68965.0,
      "ma5": 69065.0,
      "ma25": 68865.2,
      "rsi": 53.6,
      "macd": 62.87,
      "macd_signal": 41.73,
      "macd_hist": 21.14,
      "bb_upper": 69129.91,
      "bb_lower": 68668.59
    },
    {
      "time": "2026-07-11 00:40",
      "open": 68960.0,
      "high": 68970.0,
      "low": 68780.0,
      "close": 68840.0,
      "ma5": 69021.0,
      "ma25": 68875.0,
      "rsi": 54.7,
      "macd": 47.84,
      "macd_signal": 42.96,
      "macd_hist": 4.89,
      "bb_upper": 69128.73,
      "bb_lower": 68674.27
    },
    {
      "time": "2026-07-11 00:45",
      "open": 68855.0,
      "high": 68895.0,
      "low": 68805.0,
      "close": 68880.0,
      "ma5": 68982.0,
      "ma25": 68884.8,
      "rsi": 54.2,
      "macd": 38.71,
      "macd_signal": 42.11,
      "macd_hist": -3.4,
      "bb_upper": 69129.18,
      "bb_lower": 68677.32
    },
    {
      "time": "2026-07-11 00:50",
      "open": 68885.0,
      "high": 68975.0,
      "low": 68865.0,
      "close": 68960.0,
      "ma5": 68948.0,
      "ma25": 68890.2,
      "rsi": 53.5,
      "macd": 37.49,
      "macd_signal": 41.18,
      "macd_hist": -3.69,
      "bb_upper": 69133.35,
      "bb_lower": 68688.65
    },
    {
      "time": "2026-07-11 00:55",
      "open": 68960.0,
      "high": 68995.0,
      "low": 68935.0,
      "close": 68995.0,
      "ma5": 68928.0,
      "ma25": 68896.2,
      "rsi": 52.6,
      "macd": 38.91,
      "macd_signal": 40.73,
      "macd_hist": -1.82,
      "bb_upper": 69139.99,
      "bb_lower": 68701.01
    },
    {
      "time": "2026-07-11 01:00",
      "open": 69030.0,
      "high": 69085.0,
      "low": 69030.0,
      "close": 69085.0,
      "ma5": 68952.0,
      "ma25": 68909.8,
      "rsi": 58.5,
      "macd": 46.75,
      "macd_signal": 41.93,
      "macd_hist": 4.82,
      "bb_upper": 69157.0,
      "bb_lower": 68714.0
    },
    {
      "time": "2026-07-11 01:05",
      "open": 69070.0,
      "high": 69150.0,
      "low": 69070.0,
      "close": 69080.0,
      "ma5": 69000.0,
      "ma25": 68921.2,
      "rsi": 61.5,
      "macd": 51.96,
      "macd_signal": 43.94,
      "macd_hist": 8.03,
      "bb_upper": 69174.44,
      "bb_lower": 68715.56
    },
    {
      "time": "2026-07-11 01:10",
      "open": 69095.0,
      "high": 69125.0,
      "low": 69060.0,
      "close": 69095.0,
      "ma5": 69043.0,
      "ma25": 68931.2,
      "rsi": 67.6,
      "macd": 56.65,
      "macd_signal": 46.48,
      "macd_hist": 10.17,
      "bb_upper": 69180.83,
      "bb_lower": 68744.17
    },
    {
      "time": "2026-07-11 01:15",
      "open": 69100.0,
      "high": 69175.0,
      "low": 69100.0,
      "close": 69175.0,
      "ma5": 69086.0,
      "ma25": 68946.0,
      "rsi": 66.3,
      "macd": 66.06,
      "macd_signal": 50.4,
      "macd_hist": 15.66,
      "bb_upper": 69204.54,
      "bb_lower": 68758.46
    },
    {
      "time": "2026-07-11 01:20",
      "open": 69180.0,
      "high": 69200.0,
      "low": 69145.0,
      "close": 69165.0,
      "ma5": 69120.0,
      "ma25": 68960.4,
      "rsi": 63.9,
      "macd": 71.89,
      "macd_signal": 54.7,
      "macd_hist": 17.19,
      "bb_upper": 69228.23,
      "bb_lower": 68762.27
    },
    {
      "time": "2026-07-11 01:25",
      "open": 69155.0,
      "high": 69200.0,
      "low": 69135.0,
      "close": 69180.0,
      "ma5": 69139.0,
      "ma25": 68976.2,
      "rsi": 58.2,
      "macd": 76.82,
      "macd_signal": 59.12,
      "macd_hist": 17.7,
      "bb_upper": 69252.67,
      "bb_lower": 68761.33
    },
    {
      "time": "2026-07-11 01:30",
      "open": 69185.0,
      "high": 69210.0,
      "low": 69185.0,
      "close": 69205.0,
      "ma5": 69164.0,
      "ma25": 68988.8,
      "rsi": 58.8,
      "macd": 81.81,
      "macd_signal": 63.66,
      "macd_hist": 18.15,
      "bb_upper": 69278.09,
      "bb_lower": 68765.41
    },
    {
      "time": "2026-07-11 01:35",
      "open": 69210.0,
      "high": 69230.0,
      "low": 69170.0,
      "close": 69185.0,
      "ma5": 69182.0,
      "ma25": 69006.4,
      "rsi": 53.9,
      "macd": 83.19,
      "macd_signal": 67.57,
      "macd_hist": 15.63,
      "bb_upper": 69291.86,
      "bb_lower": 68784.64
    },
    {
      "time": "2026-07-11 01:40",
      "open": 69190.0,
      "high": 69215.0,
      "low": 69175.0,
      "close": 69175.0,
      "ma5": 69182.0,
      "ma25": 69021.6,
      "rsi": 55.9,
      "macd": 82.53,
      "macd_signal": 70.56,
      "macd_hist": 11.97,
      "bb_upper": 69286.25,
      "bb_lower": 68830.25
    },
    {
      "time": "2026-07-11 01:45",
      "open": 69185.0,
      "high": 69210.0,
      "low": 69185.0,
      "close": 69200.0,
      "ma5": 69189.0,
      "ma25": 69034.0,
      "rsi": 70.4,
      "macd": 83.06,
      "macd_signal": 73.06,
      "macd_hist": 10.0,
      "bb_upper": 69295.65,
      "bb_lower": 68851.85
    },
    {
      "time": "2026-07-11 01:50",
      "open": 69205.0,
      "high": 69240.0,
      "low": 69185.0,
      "close": 69210.0,
      "ma5": 69195.0,
      "ma25": 69044.6,
      "rsi": 90.2,
      "macd": 83.33,
      "macd_signal": 75.11,
      "macd_hist": 8.22,
      "bb_upper": 69306.78,
      "bb_lower": 68868.72
    },
    {
      "time": "2026-07-11 01:55",
      "open": 69210.0,
      "high": 69210.0,
      "low": 69180.0,
      "close": 69195.0,
      "ma5": 69193.0,
      "ma25": 69056.0,
      "rsi": 86.2,
      "macd": 81.39,
      "macd_signal": 76.37,
      "macd_hist": 5.03,
      "bb_upper": 69318.2,
      "bb_lower": 68870.8
    },
    {
      "time": "2026-07-11 02:00",
      "open": 69205.0,
      "high": 69220.0,
      "low": 69160.0,
      "close": 69175.0,
      "ma5": 69191.0,
      "ma25": 69068.8,
      "rsi": 78.7,
      "macd": 77.36,
      "macd_signal": 76.57,
      "macd_hist": 0.79,
      "bb_upper": 69325.82,
      "bb_lower": 68873.18
    },
    {
      "time": "2026-07-11 02:05",
      "open": 69185.0,
      "high": 69225.0,
      "low": 69180.0,
      "close": 69205.0,
      "ma5": 69197.0,
      "ma25": 69086.0,
      "rsi": 78.4,
      "macd": 75.7,
      "macd_signal": 76.39,
      "macd_hist": -0.69,
      "bb_upper": 69334.14,
      "bb_lower": 68872.36
    },
    {
      "time": "2026-07-11 02:10",
      "open": 69195.0,
      "high": 69205.0,
      "low": 69195.0,
      "close": 69205.0,
      "ma5": 69198.0,
      "ma25": 69098.6,
      "rsi": 71.4,
      "macd": 73.54,
      "macd_signal": 75.82,
      "macd_hist": -2.28,
      "bb_upper": 69344.01,
      "bb_lower": 68873.49
    }
  ],
  "data_source": "NIY=F",
  "timeframes": {
    "15m": {
      "label": "15分足",
      "signal": "様子見",
      "score": -1.5,
      "score_normalized": -21,
      "close": 69205.0,
      "time": "2026-07-11 02:00",
      "data_source": "NIY=F"
    },
    "1h": {
      "label": "1時間足",
      "signal": "買い",
      "score": 3,
      "score_normalized": 43,
      "close": 69205.0,
      "time": "2026-07-11 02:00",
      "data_source": "NIY=F"
    }
  },
  "composite": "買い優勢",
  "economic_events": {
    "upcoming_events": [
      {
        "time": "2026-07-30 03:00",
        "label": "FOMC政策金利発表",
        "hours_until": 456.8
      },
      {
        "time": "2026-07-31 12:00",
        "label": "日銀金融政策決定会合(結果発表・目安)",
        "hours_until": 489.8
      },
      {
        "time": "2026-08-07 21:30",
        "label": "米雇用統計(NFP)",
        "hours_until": 667.3
      },
      {
        "time": "2026-09-04 21:30",
        "label": "米雇用統計(NFP)",
        "hours_until": 1339.3
      },
      {
        "time": "2026-09-17 03:00",
        "label": "FOMC政策金利発表",
        "hours_until": 1632.8
      }
    ],
    "warning": false,
    "warning_events": []
  }
}